nonebot_plugin_forwarder/__init__.py
nonebot_plugin_forwarder/config.py
nonebot_plugin_forwarder-2.1.6.dist-info/LICENSE
nonebot_plugin_forwarder-2.1.6.dist-info/METADATA
nonebot_plugin_forwarder-2.1.6.dist-info/WHEEL
nonebot_plugin_forwarder-2.1.6.dist-info/top_level.txt
nonebot_plugin_forwarder-2.1.6.dist-info/RECORD
