Metadata-Version: 2.1
Name: nonebot-plugin-forwarder
Version: 2.1.6
Summary: A plugin based on NoneBot2, which can broadcast message from Source Groups to Destination Groups.
Home-page: https://github.com/ninthseason/nonebot_plugin_forwarder
Author: Kl1nge5
Project-URL: Bug Tracker, https://github.com/ninthseason/nonebot_plugin_forwarder/issues
Classifier: Programming Language :: Python :: 3
Classifier: License :: OSI Approved :: GNU General Public License v3 (GPLv3)
Classifier: Operating System :: OS Independent
Requires-Python: >=3.7
License-File: LICENSE
Requires-Dist: nonebot2 (>=2.0.0b2)
Requires-Dist: nonebot-adapter-onebot (>=2.0.0b1)
